src/Mail.py
src/Sendemail.py
PyfEMail-0.0.1.dist-info/LICENSE
PyfEMail-0.0.1.dist-info/METADATA
PyfEMail-0.0.1.dist-info/WHEEL
PyfEMail-0.0.1.dist-info/top_level.txt
PyfEMail-0.0.1.dist-info/RECORD
