Metadata-Version: 2.1
Name: PyfEMail
Version: 0.0.1
Summary: A EMail Library.
Home-page: https://pypi.org
Author: we-code
Author-email: pyf2013@126.com
License: UNKNOWN
Platform: UNKNOWN
License-File: LICENSE
Requires-Dist: requests
